{
	"schemaVersion": 1,
	"id": "my-fabric-mod",
	"version": "${version}",
	"name": "My Fabric Mod",
	"description": "This is my first Mod Coded Ever!",
	"authors": [
		"Freetime Maker!"
	],
	"contact": {
		"sources": "https://github.com/FreetimeMaker/my-fabric-mod-template-1.21.1/"
	},
	"license": "MIT",
	"icon": "assets/my-fabric-mod/Icon.png",
	"environment": "*",
	"entrypoints": {
		"main": [
			"com.freetime.MyFabricMod"
		],
		"fabric-datagen": [
			"com.freetime.MyFabricModDataGenerator"
		],
		"client": [
			"com.freetime.MyFabricModClient"
		],
	},
	"mixins": [
		"my-fabric-mod.mixins.json"
	],
	"depends": {
		"fabricloader": ">=0.16.10",
		"minecraft": "~1.21.1",
		"java": ">=21",
		"fabric-api": "*"
	},
	"suggests": {
		"another-mod": "*"
	}
}